airo_models/__init__.py
airo_models/files.py
airo_models/urdf.py
airo_models/__pycache__/__init__.cpython-310.pyc
airo_models/__pycache__/files.cpython-310.pyc
airo_models/__pycache__/urdf.cpython-310.pyc
airo_models/arms/ur3e/ur3e.urdf
airo_models/arms/ur3e/collision/base.mtl
airo_models/arms/ur3e/collision/base.obj
airo_models/arms/ur3e/collision/forearm.mtl
airo_models/arms/ur3e/collision/forearm.obj
airo_models/arms/ur3e/collision/shoulder.mtl
airo_models/arms/ur3e/collision/shoulder.obj
airo_models/arms/ur3e/collision/upperarm.mtl
airo_models/arms/ur3e/collision/upperarm.obj
airo_models/arms/ur3e/collision/wrist1.mtl
airo_models/arms/ur3e/collision/wrist1.obj
airo_models/arms/ur3e/collision/wrist2.mtl
airo_models/arms/ur3e/collision/wrist2.obj
airo_models/arms/ur3e/collision/wrist3.mtl
airo_models/arms/ur3e/collision/wrist3.obj
airo_models/arms/ur3e/visual/base.blend1
airo_models/arms/ur3e/visual/base.mtl
airo_models/arms/ur3e/visual/base.obj
airo_models/arms/ur3e/visual/base_cable.mtl
airo_models/arms/ur3e/visual/base_cable.obj
airo_models/arms/ur3e/visual/base_cable_labels.mtl
airo_models/arms/ur3e/visual/base_cable_labels.obj
airo_models/arms/ur3e/visual/forearm.mtl
airo_models/arms/ur3e/visual/forearm.obj
airo_models/arms/ur3e/visual/shoulder.mtl
airo_models/arms/ur3e/visual/shoulder.obj
airo_models/arms/ur3e/visual/upperarm.mtl
airo_models/arms/ur3e/visual/upperarm.obj
airo_models/arms/ur3e/visual/ur3e_color.png
airo_models/arms/ur3e/visual/ur3e_normal.png
airo_models/arms/ur3e/visual/ur3e_occlusion_roughness_metallic.png
airo_models/arms/ur3e/visual/wrist1.mtl
airo_models/arms/ur3e/visual/wrist1.obj
airo_models/arms/ur3e/visual/wrist2.mtl
airo_models/arms/ur3e/visual/wrist2.obj
airo_models/arms/ur3e/visual/wrist3.mtl
airo_models/arms/ur3e/visual/wrist3.obj
airo_models/arms/ur5e/ur5e.urdf
airo_models/arms/ur5e/collision/base.mtl
airo_models/arms/ur5e/collision/base.obj
airo_models/arms/ur5e/collision/forearm.mtl
airo_models/arms/ur5e/collision/forearm.obj
airo_models-0.0.12.dist-info/licenses/LICENSE
airo_models-0.0.12.dist-info/METADATA
airo_models-0.0.12.dist-info/WHEEL
airo_models-0.0.12.dist-info/top_level.txt
airo_models-0.0.12.dist-info/RECORD
