Metadata-Version: 2.4
Name: airo-models
Version: 0.0.12
Summary: Curated URDFs and 3D models of the robots and gripper used at airo.
Author-email: Andreas Verleysen <andreas.verleysen@ugent.be>, Victor-Louis De Gusseme <victorlouisdg@gmail.com>, Mathieu De Coster <mathieu.decoster@ugent.be>
Project-URL: Homepage, https://github.com/airo-ugent/airo-models
Project-URL: Issues, https://github.com/airo-ugent/airo-models/issues
Classifier: Programming Language :: Python :: 3
Classifier: License :: OSI Approved :: MIT License
Classifier: Operating System :: OS Independent
Requires-Python: >=3.10
License-File: LICENSE
Requires-Dist: xmltodict>=1.0.2
Dynamic: license-file
